everai_autoscaler/model/__init__.py
everai_autoscaler/model/action.py
everai_autoscaler/model/autoscaler.py
everai_autoscaler/model/autoscaler.pyi
everai_autoscaler/model/builtin_autoscaler.py
everai_autoscaler/model/builtin_autoscaler.pyi
everai_autoscaler/model/decorator.py
everai_autoscaler/model/factors.py
everai_autoscaler-0.1.23.dist-info/METADATA
everai_autoscaler-0.1.23.dist-info/WHEEL
everai_autoscaler-0.1.23.dist-info/top_level.txt
everai_autoscaler-0.1.23.dist-info/RECORD
